proairtable/__init__.py
proairtable/_client.py
proairtable/_schema.py
proairtable/fields/__init__.py
proairtable/fields/base.py
proairtable/fields/date.py
proairtable/fields/string.py
proairtable-0.1.0.dist-info/LICENSE
proairtable-0.1.0.dist-info/WHEEL
proairtable-0.1.0.dist-info/METADATA
proairtable-0.1.0.dist-info/RECORD
